whom/__init__.py
whom/py.typed
whom-1.0.1.dist-info/licenses/LICENSE
whom-1.0.1.dist-info/METADATA
whom-1.0.1.dist-info/WHEEL
whom-1.0.1.dist-info/top_level.txt
whom-1.0.1.dist-info/RECORD
